shopcloud_proxy_client/__init__.py
shopcloud_proxy_client/client.py
shopcloud_proxy_client-1.7.0.dist-info/METADATA
shopcloud_proxy_client-1.7.0.dist-info/WHEEL
shopcloud_proxy_client-1.7.0.dist-info/top_level.txt
shopcloud_proxy_client-1.7.0.dist-info/RECORD
